binod3/__init__.py
binod3/__main__.py
binod_magic-1.0.3.dist-info/LICENSE
binod_magic-1.0.3.dist-info/METADATA
binod_magic-1.0.3.dist-info/WHEEL
binod_magic-1.0.3.dist-info/entry_points.txt
binod_magic-1.0.3.dist-info/top_level.txt
binod_magic-1.0.3.dist-info/RECORD
